{"field":{"screen":{"title":"Commissioning Powerroc Report ","preview_title":"Preview","page_title_1":"First Page","page_title_2":"Second Page","page_title_3":"Page-3"},"form":{"machine":"Machine Model","callno":"JobCard No","customer_name":"Customer Name","dealer_name":"Dealer Name","address":"Dealer Address","dealer_city":"Dealer City","phone_num":"Phone Number","mac_loc":"Machine Location","designation":"Designation","worksite_address":"Customer Address","fax_num":"Fax Number","applied_savedetails":"Applied Segment","commission":"Commissioning Details","eqip_sino":"Machine SI No","dur_from":"Inspection Date (From)","dur_to":"Inspection Date (To)","date_of_com":"DOC","hmr":"HMR","unit":"Unit Particulars","engine":"Track Drive Model","rotation_gear":"Rotation Gear Box Model","rotation_motor":"Rotation Motor Model","feed_motor":"Feed Motor Model","serial":"Track Drive Serial Number","serial_rotation":"Rotation Gear Box Serial Number","serial_rotation_motor":"Rotation Motor Serial Number","serial_feed_motor":"Feed Motor Serial Number","air":"Air System","comp_model":"Compressor Model","comp_sino":"Compressor SINo","engine_model":"Engine Model","engine_sino":"Engine  Serial Number","mch_airpres_low":"System Air Pressure Low Value","mch_airpress":"System Air Pressure ","mch_airpres_high":"System Air Pressure High Value","compr_airpres_low":"Service Air Pressure Low Value","compr_low":"Service Air Pressure ","compr_airpres_high":"Service Air Pressure High Value","eng_oilpres_low":"Engine Oil Pressure Low Value","eng_press":"Engine Oil Pressure ","eng_oilpres_high":"Engine Oil Pressure High Value","coolant_low":"Coolant Temp low(°C)","coolant_high":"Coolant Temp High(°C)","drill":"Drill String","drillpipe_dia":"Drill Pipe Dia(mm)","drillpipe_length":"Drill Pipe length(meters)","hammer_dia":"Hammer Dia(mm)","hammer_length":"Hammer length(meters)","bitdia":"Bit Dia(mm)","hole_depth":"Hole Depth(meters)","multi_rod":"Multi Rod","strata":"Strata","multi_rodval":"Multi Rod Value","formation":"Formation Strata","rock_type":"RockType Strata","rock_hardness":"Rock Hardness","meters":"Meters Drilled","name_rock":" Name Of the Operators Trained","meter_drilled":"Meter Drilled Strata Value","mtr_drilled":"Meter Drilled ","remark":"Remarks If any by Customer","sename":"Service Engineer Name","cuname":"Customer Name","serengi_sign":"Service Engineer Sign","customer_sign":"Customer Sign","geo_location":"Live Location","dealer_code":"Dealer Code","state":"Dealer State","pic":"Picture","picture_details":"Picture","photo_1":"Machine photograph(Front)(Focus through Rotation gearbox till Centralizer visible with Drill pipe covered)","photo_2":"Machine photograph(Rear)(Rear Part of the machine where the inlet air pressure gauge showing the value clearly with Feeder down)","photo_3":"Machine photograph(Parameters/Dashboard)","comp_address":"Company Address","state1":"State","pin_code":"Pincode","city":"City ","comp_name":"Company name"}},"toastMessages":{"success":"Report submitted successfully.","service_exception":"Service Exception","get_date_error":"Failed to get the date","load_controller_file_error":"Unable to load controller file","load_config_files_error":"Unable to load config files","delete_config_files_error":"Failed to delete config files","form_fields_mandatory_alert":"Please fill all the mandatory fields","save_draft_success":"Form saved successfully","save_draft_error":"Unable to save the form","form_submit_alert":"Do you want to submit?","form_submit_internet_connection_error":"Internet connection is required to proceed further.","form_submit_success":"Form Submitted  successfully","form_submit_error":"Failed to send the form data","save_pdf_data_error":"Unable to send pdf data","save_pdf_html_data_error":"Unable to send pdf data","form_back_click_alert":"Do you want to go back?","form_back_click_data_alert":"Entered data will be lost. Do you want to go back?","form_back_click_auto_save_alert":"Do you want to save the the data in draft and go back?","create_trans_key_error":"Failed to create transaction key file","error_complaint_exists":"There is an active complaint with reference number #: ref_no #","error_call_insert":"Failed to register your complaint","error_parts_insert":"Failed to register your complaint","error_ancillary_insert":"Failed to register your complaint"},"confirmMessages":{"form_submit_alert":"Do you want to submit?","TurnOnAutomaticDateTime":"Please turn on automatic date and time settings.","form_back_click_data_alert":"Entered data will be lost. Do you want to go back?","form_back_click_auto_save_alert":"Do you want to save the the data in draft and go back?"},"wFlowEvents":{},"placeholder":{}}