{
    "field": {
		"screen": {
			"title": "Call Details"
		},
		"header" : {
			"attachments" : "Attachments",
			"event_log":"Timeline",
			"machine_info":"Machine Information",
			"problem_description":"Problem Description",
			"customer_info":"Customer Information",
			"engineer_info":"Engineer Information",
			"created_on":"Created On",
			"expected_on":"Expected On",
			"enquiry_info":"Enquiry Information",
			"follow_up":"Follow Up",
			"asset_id":"Asset Id",
			"feedback":"Feedback",
			"equipment_id":"Equipment Id",
			"equipment_category":"Equipment Category",
			"equipment_type":"Equipment Type",
			"installation_date":"Installation Date",
			"Rating_title":"Rating for this ticket"
			
			
		},
		"form": {
			"call_info": "Call Info",
			"schedule_info": "Schedule Date",
			"actual_info": "Actual Date",
			"date_info": "Date Info",
			"machine_info": "Machine Info",
			"created_on": "Created On",
			"customer_info": "Customer Info",
			"attachment_info":"Attachments",
			"assigned_on": "Assigned On",
			"sch_start_on": "Sch. Start On",
			"sch_finish_on": "Sch. Finish On",
			"act_start_on": "Act. Start On",
			"act_finish_on": "Act. Finish On",
			"closed_on":"Closed On"
			
		},
		"timeline":{
			"OPEN": "Created",
			"ASSIGN": "Assigned",
			"TripStart": "Trip Started",
			"TripFinish": "Trip Finished",
			"START": "Work Started",
			"WORKCOMPLETE": "Work Finished",
			"MEETINGFINISH":"Meeting Finish",
			"MEETINGSTART":"Meeting Start",
			"SAVEFORASSIGN": "Save For Assign",
			"fsr_form": "Field service report",
			"commreport_form": "Dynapac comm report ",
			"commissionscc384_form": "commission_cc384_report",
			"commissionscc425_form": "commission_cc455_report",
			"commissionscc125_form": "commission_cc125_report",
			"fiftyhrsscc125_form": "50hrs_cc125_report",
			"fiftyhrsscc384_form": "50hrs_cc384_report",
			"fiftyhrsca255_form": "50hrs_ca255_report",
			"fiftyhrsscc425_form": "fiffty_cc425_report",
			"fiftyhrspav_form": "50hrs_pavers_report",
			"fivhrsscc125_form": "500hrs_cc125_report",
			"fivhrssca255_form": "500hrs_ca255_report",
			"fivehrsscc425_form": "five_cc425_report",
			"fivhrsscc384_form": "500hrs_cc384_report",
			"fivhrspav_form": "500hrs_pavers_report",
			"dyfsone_form": "Dynapac fiftyhrs report",
			"dyfsthird_form": "Dynapac thirdcoupon report",
			"dyfssecond_form": "Dynapac second report",
			"geninsca255_form": "generalinspection_ca255_report",
			"geninscc125_form": "generalinspection_cc125_report",
			"geninscc384_form": "generalinspection_cc384_report",
			"geninscc425_form": "generalinspection_cc425_report",
			"geninspav_form": "generalinspection_pavers_report",
			"marini_inspec_form": "Dynapac Marini report",
			"marini_serv_form": "Dynapac Marini report",
			"dynapaccomm_form": "dyn_pavers_comm_report",
			"100hrs_pav_report_form": "100hrs_pav_report",
			"pav_schedule_visit_report_form": "pav_schedule_visit_report",
			"1500hrs_pav_report_form": "1500hrs_pav_report",
			"sevhrsscc125_form": "750hrs_cc125_report",
			"tenhrsscc125_form": "1000hrs_cc125_report",
			"tenhrssca255_form": "1000hrs_ca255_report",
			"tenthousand425_form": "tenthousand_cc425_report",
            "tenthousand384_form": "1000hrs_cc384_report",
			"tenhrspav_form": "1000hrs_pavers_report",
			"250hrs_cc125_form": "250hrs_cc125_report",
			"commissioncp_form": "CP Roller Commisioning Report",
			"dynapac_flup_mtng_repo_form": "Meeting Report PL",
			"dynapac_mtng_repo_form": "Generate Visit Report",
			"shedule_maintenance_cp_form": "CP Roller Shedule Maintenance Report",
			"generalinspect_form": "Dynapac comm report",
			"warranty_form": "warrenty_report",
			"COMPLETE": "Completed"
		}
    },
	"toastMessages": {
		"load_controller_file_error": "Unable to load controller file",
		"load_config_files_error": "Unable to load config files"
	}
}
