<?xml version="1.0"?><ui_configuration><content><content_1><field id="salesinvoice_number_filter"><type>w_textbox</type></field><field id="customer_order_number_filter"><type>w_textbox</type></field><field id="acc_sys_no_filter"><type>w_textbox</type></field><field id="salesinvoice_category_filter"><type>w_dropdownlist</type><dataTextField>description</dataTextField><dataValueField>code</dataValueField><childFieldID>manage_salesinvoice_master_spares_salesinvoice_type_filter</childFieldID><dataSource><informationType>"SALESINVOICECATEGORY_LIST"</informationType></dataSource></field><field id="salesinvoice_type_filter"><type>w_dropdownlist</type><dataTextField>description</dataTextField><dataValueField>code</dataValueField><dataSource><informationType>"SALESINVOICETYPE_LIST_LINKED"</informationType><searchField1>#manage_salesinvoice_master_spares_salesinvoice_category_filter</searchField1></dataSource></field><field id="salesinvoice_status_filter"><type>w_multiselect</type><dataTextField>description</dataTextField><dataValueField>code</dataValueField><childFieldID>manage_salesinvoice_master_spares_salesinvoice_type_filter</childFieldID><dataSource><informationType>"SALESINVOICESTATUS_LIST"</informationType></dataSource></field><field id="buyer_reference_number_filter"><type>w_textbox</type></field><field id="other_reference_number_filter"><type>w_textbox</type></field><field id="fiscal_year_filter"><type>w_dropdownlist</type><dataTextField>text</dataTextField><dataValueField>value</dataValueField><dataSource>[{"text": "2016-2017", "value": "16-17"},{"text": "2017-2018", "value": "17-18"},{"text": "2018-2019", "value": "18-19"}]</dataSource><template>description</template></field><field id="buyer_code_filter"><type>w_combobox</type><dataTextField>name</dataTextField><serverFiltering>true</serverFiltering><dataValueField>id</dataValueField><childFieldID>manage_salesinvoice_master_spares_buyer_location_code_filter</childFieldID><dataSource><applicationName>common_modules</applicationName><serviceName>retrieve_listof_values_for_searchcondition</serviceName><inputParameter><p_inputparam_xml>&lt;inputparam&gt;&lt;lov_code_type&gt;"CUSTOMER_LIST_SEARCH_WO_ZZZ"&lt;/lov_code_type&gt;&lt;search_field_1&gt;$manage_salesinvoice_master_spares.variable.custom.buyer_code_filter_serverFilterValue&lt;/search_field_1&gt;&lt;/inputparam&gt;</p_inputparam_xml></inputParameter></dataSource></field><field id="buyer_location_code_filter"><type>w_combobox</type><dataTextField>description</dataTextField><serverFiltering>true</serverFiltering><dataValueField>code</dataValueField><dataSource><applicationName>common_modules</applicationName><serviceName>retrieve_listof_values_for_searchcondition</serviceName><inputParameter><p_inputparam_xml>&lt;inputparam&gt;&lt;lov_code_type&gt;"CUSTOMERLOCATION_LIST_LINKED"&lt;/lov_code_type&gt;&lt;search_field_1&gt;#manage_salesinvoice_master_spares_buyer_code_filter&lt;/search_field_1&gt;&lt;/inputparam&gt;</p_inputparam_xml></inputParameter></dataSource></field><field id="item_code_filter"><type>w_combobox</type><dataTextField>description</dataTextField><serverFiltering>true</serverFiltering><dataValueField>code</dataValueField><dataSource><applicationName>common_modules</applicationName><serviceName>retrieve_listof_values_for_searchcondition</serviceName><inputParameter><p_inputparam_xml>&lt;inputparam&gt;&lt;lov_code_type&gt;"ITEMCODE_SEARCH_SPARE"&lt;/lov_code_type&gt;&lt;search_field_1&gt;$manage_salesinvoice_master_spares.variable.custom.item_code_filter_serverFilterValue&lt;/search_field_1&gt;&lt;/inputparam&gt;</p_inputparam_xml></inputParameter></dataSource></field><field id="date_type_filter"><type>w_dropdownlist</type><dataSource>[{"text": "Creation Date ", "value": "C"}]</dataSource><dataTextField>text</dataTextField><dataValueField>value</dataValueField><template>description</template></field><field id="from_date_filter"><type>w_datepicker</type></field><field id="to_date_filter"><type>w_datepicker</type></field><field id="warehouse_id_filter"><type>w_combobox</type><dataTextField>description</dataTextField><dataValueField>code</dataValueField><serverFiltering>true</serverFiltering><dataSource><informationType>"WAREHOUSE_LIST"</informationType><searchField1>$manage_salesinvoice_master_spares.variable.custom.warehouse_id_filter_serverFilterValue</searchField1></dataSource></field><field id="dealer_id_filter"><type>w_combobox</type><dataTextField>description</dataTextField><dataValueField>code</dataValueField><serverFiltering>true</serverFiltering><dataSource><informationType>"DEALER_LIST"</informationType><searchField1>$manage_salesinvoice_master_spares.variable.custom.dealer_id_filter_serverFilterValue</searchField1></dataSource></field></content_1></content><grid><grid_1><field id="settings_icon"><display>true</display><width>70px</width><template>&lt;div style = "cursor: pointer;" data-widget-type = "w_link" data-link-type = "actions" title="My Actions"&gt;&lt;img src="../../common/images/double_arrow.png" style="width: 12px;margin-left: 15px;"/&gt;&lt;/div&gt;</template></field><field id="salesinvoice_no"><display>true</display><width>120px</width><template>false</template></field><field id="acc_sys_no"><display>true</display><width>120px</width><template>false</template></field><field id="buyer_id_desc"><display>true</display><width>120px</width><template>false</template></field><field id="salesinvoice_category_description"><display>true</display><width>120px</width><template>false</template></field><field id="salesinvoice_type_description"><display>true</display><width>120px</width><template>false</template></field><field id="salesinvoice_status_description"><display>true</display><width>110px</width><template>false</template></field><field id="salesinvoice_date"><display>true</display><width>100px</width><template>#if (kendo.toString(salesinvoice_date) =="") {# #} else {#${kendo.toString(new Date(salesinvoice_date),"dd-MM-yyyy")} #}#</template></field><field id="warehouse_id_desc"><display>true</display><width>120px</width><template>false</template></field><field id="salesinvoice_net_amount"><display>true</display><width>120px</width><template>false</template></field><field id="customer_order_no"><display>true</display><width>100px</width><template>#if (kendo.toString(customer_order_no) == "") {# #} else {# &lt;span data-widget-type = "w_link" data-link-type = "customer_order_reference" style = "text-decoration: underline; color: blue; cursor: pointer" &gt;${customer_order_no}&lt;/span&gt; #} #</template></field></grid_1></grid><datasource><datasource_1><field id="salesinvoice_no"/><field id="acc_sys_no"/><field id="buyer_id_desc"/><field id="salesinvoice_date"/><field id="salesinvoice_category"/><field id="salesinvoice_type"/><field id="org_level_no"/><field id="org_level_code"/><field id="salesinvoice_status"/><field id="warehouse_id_desc"/><field id="buyer_customer_id"/><field id="buyer_customer_location_code"/><field id="consignee_customer_id"/><field id="consignee_customer_location_code"/><field id="seller_location_code"/><field id="final_destination"/><field id="salesinvoice_file_no"/><field id="salesinvoice_net_amount"/><field id="customer_order_no"/><field id="rec_tstamp"/><field id="salesinvoice_category_description"><codeType>SALESINVOICECATEGORY_LIST</codeType><codeField>salesinvoice_category</codeField></field><field id="salesinvoice_type_description"><codeType>SALESINVOICETYPE_LIST</codeType><codeField>salesinvoice_type</codeField></field><field id="salesinvoice_status_description"><codeType>SALESINVOICESTATUS_LIST</codeType><codeField>salesinvoice_status</codeField></field></datasource_1></datasource></ui_configuration>