<?xml version="1.0"?><ui_configuration><content><content_1><field id="call_number_filter"><type>w_textbox</type></field><field id="call_act_finish_on_date_filter"><type>w_datepicker</type></field><field id="feedback_submit_date_filter"><type>w_datepicker</type></field></content_1></content><datasource><datasource_1><field id="cust_id"/><field id="cust_name"/><field id="request_ref_no"/><field id="call_category"/><field id="call_type"/><field id="call_status"/><field id="billable_nonbillable_ind"/><field id="call_status_desc"/><field id="workflow_stage_no"/><field id="workflow_stage_no_desc"/><field id="priority_cd"/><field id="cust_contact_name"/><field id="cust_contact_no"/><field id="cust_contact_email"/><field id="company_location_code"/><field id="asset_location_reported"/><field id="org_level_no"/><field id="org_level_code"/><field id="equipment_id"/><field id="asset_desc"/><field id="created_on_date"/><field id="created_on_hour"/><field id="created_on_minute"/><field id="sch_start_on_date"/><field id="sch_start_on_hour"/><field id="sch_start_on_minute"/><field id="sch_finish_on_date"/><field id="sch_finish_on_hour"/><field id="sch_finish_on_minute"/><field id="act_start_on_date"/><field id="act_start_on_hour"/><field id="act_start_on_minute"/><field id="act_finish_on_date"/><field id="act_finish_on_hour"/><field id="act_finish_on_minute"/><field id="call_act_finish_on_date"/><field id="feedback_submit_date"/><field id="plan_duration"/><field id="plan_duration_uom"/><field id="plan_work"/><field id="plan_work_uom"/><field id="act_duration"/><field id="act_work"/><field id="asset_id"/><field id="customer_requirement"/><field id="additional_information"/><field id="assigned_to_emp_id"/><field id="assigned_to_emp_name"/><field id="call_mapped_to_emp_id"/><field id="asset_in_warranty_ind"/><field id="job_order_no"/><field id="computed_field_1"/><field id="udf_char_1"/><field id="udf_char_2"/><field id="udf_char_3"/><field id="udf_float_1"/><field id="udf_date_1"/><field id="udf_date_1_hour"/><field id="udf_date_1_minute"/><field id="udf_analysis_code1"/><field id="udf_analysis_code2"/><field id="udf_analysis_code3"/><field id="udf_analysis_code4"/><field id="rec_tstamp"/><field id="call_type_desc"/><field id="assigned_to_emp_id_description"><codeType>CALLASSIGNTOEMPLIST</codeType><codeField>assigned_to_emp_id</codeField></field><field id="call_category_description"><codeType>CALLCATEGORY</codeType><codeField>call_category</codeField></field><field id="call_priority_description"><codeType>CALLPRIORITY</codeType><codeField>priority_cd</codeField></field><field id="call_status_description"><codeType>CALLSTATUS</codeType><codeField>call_status</codeField></field><field id="company_location_description"><codeType>COMPANYLOCATION</codeType><codeField>company_location_code</codeField></field><field id="computed_field_1_description"><codeType>EXPENSESTATUS_DESC</codeType><codeField>computed_field_1</codeField></field><field id="org_level_code_description"><codeType>ORGLEVELCODE</codeType><codeField>org_level_code</codeField></field><field id="org_level_no_description"><codeType>ORGLEVELNO</codeType><codeField>org_level_no</codeField></field></datasource_1></datasource><grid><grid_1><field id="settings_icon"><display>true</display><width>50px</width><template>&lt;div style = "cursor: pointer;" data-widget-type = "w_link" data-link-type = "actions" title="My Actions"&gt;&lt;img src="../../common/images/double_arrow.png" style="width: 12px;margin-left: 15px;"/&gt;&lt;/div&gt;</template></field><field id="request_ref_no"><display>true</display><width>120px</width><template>false</template></field><field id="call_category"><display>false</display><width>105px</width><template>false</template></field><field id="call_category_description"><display>true</display><width>105px</width><template>false</template></field><field id="call_type"><display>false</display><width>100px</width><template>false</template></field><field id="call_type_desc"><display>true</display><width>120px</width><template>false</template></field><field id="call_status"><display>false</display><width>100px</width><template>false</template></field><field id="call_status_description"><display>true</display><width>80px</width><template>false</template></field><field id="asset_id"><display>false</display><width>120px</width><template>false</template></field><field id="cust_id"><display>false</display><width>150px</width><template>false</template></field><field id="cust_name"><display>true</display><width>100px</width><template>false</template></field><field id="equipment_id"><display>false</display><width>130px</width><template>false</template></field><field id="asset_location_reported"><display>false</display><width>150px</width><template>false</template></field><field id="priority_cd"><display>false</display><width>100px</width><template>false</template></field><field id="cust_contact_name"><display>true</display><width>100px</width><template>false</template></field><field id="assigned_to_emp_id"><display>false</display><width>120px</width><template>false</template></field><field id="assigned_to_emp_id_description"><display>false</display><width>120px</width><template>false</template></field><field id="job_order_no"><display>false</display><width>80px</width><template>false</template></field><field id="company_location_code"><display>false</display><width>100px</width><template>false</template></field><field id="org_level_no"><display>false</display><width>100px</width><template>false</template></field><field id="org_level_code"><display>false</display><width>80px</width><template>false</template></field><field id="call_act_finish_on_date"><display>true</display><width>120px</width><template>#if (kendo.toString(call_act_finish_on_date) =="") {# #} else {#${kendo.toString(new Date(call_act_finish_on_date),"dd-MM-yyyy")} #}#</template></field><field id="feedback_submit_date"><display>true</display><width>120px</width><template>#if (kendo.toString(feedback_submit_date) =="") {# #} else {#${kendo.toString(new Date(feedback_submit_date),"dd-MM-yyyy")} #}#</template></field><field id="computed_field_1_description"><display>false</display><width>100px</width><template>#if (kendo.toString(computed_field_1_description) =="0") {# #} else {# ${computed_field_1_description} #}#</template></field></grid_1></grid></ui_configuration>